{
    "filename": "d3d2cbaa-f24a-4cb7-a236-53fa514816b4___new_2017-Skoda-Rapid-Diesel-DSG-Review-6.jpg.jpeg",
    "image_width": 500,
    "image_height": 336,
    "annotations": [
        {
            "vehicle_number": "MH20EE045",
            "class_id": 0,
            "xmin": 244,
            "ymin": 114,
            "xmax": 378,
            "ymax": 149,
            "x_center": 0.622,
            "y_center": 0.391369,
            "width": 0.268,
            "height": 0.104167
        }
    ]
}